Workbook

Sheet Допущения
A1: Допущения расчёта TCO (100 магазинов, 3 года). Синие числа — вводные, их можно менять; остальное пересчитается.
A3: Параметр | B3: Значение | C3: Ед. | D3: Логика / источник
A4: Структура
A5: Магазинов в расчёте | B5: 100 | C5: шт. | D5: Условие задания 4
A6: Магазинов в сети | B6: 500 | C6: шт. | D6: info.md: «более 500 магазинов»
A7: Касс (и терминалов) в магазине | B7: 2 | C7: шт. | D7: Допущение: дрогери у дома, небольшой формат
A8: Срок службы сервера и ПК кассы | B8: 5 | C8: лет | D8: Допущение: типичный цикл замены → 20% парка в год
A9: Срок раскатки To-Be | B9: 12 | C9: мес. | D9: Цель «финальное состояние через год» (business_target.md); равномерно
A10: Доля магазино-месяцев на To-Be в год 1 | B10: =(B9+1)/(2*B9) -> 0.54166667 | C10: доля | D10: Формула: при равномерной раскатке за N мес. = (N+1)/(2N)
A11: As-Is: цены и ставки
A12: Сервер магазина | B12: 150000 | C12: ₽/шт. | D12: Допущение: сервер начального уровня / мощный ПК с RAID
A13: ПК кассы («толстый» клиент) | B13: 60000 | C13: ₽/шт. | D13: Допущение: POS-моноблок
A14: Windows Server к новому серверу | B14: 120000 | C14: ₽/шт. | D14: Допущение: лицензия Standard + CAL
A15: Лицензия SQL Server | B15: 0 | C15: ₽/шт. | D15: Не учитываем (консервативно): часть магазинов на PostgreSQL, доля неизвестна; в артефакте 1 — бесплатный SQL Express, в info.md — платный SQL
A16: Резервное копирование и антивирус сервера | B16: 8000 | C16: ₽/магазин/год | D16: Допущение
A17: Сопровождение кассового ПО и драйверов | B17: 10000 | C17: ₽/касса/год | D17: Допущение; новый драйвер — 3 недели разработки (INC-8415)
A18: Инженеры поддержки серверов | B18: 4 | C18: чел. на 100 маг. | D18: Допущение: ≈ 25 серверов на инженера; 40% ИТ-бюджета — на серверы (tasks/1.md)
A19: Стоимость инженера с налогами | B19: 200000 | C19: ₽/мес. | D19: Допущение: рынок 2026 г.
A20: Выездов на магазин в год | B20: 1.5 | C20: шт. | D20: Допущение: отказы сервера и обслуживание (INC-8433)
A21: Стоимость выезда (дорога, суточные, гостиница) | B21: 30000 | C21: ₽ | D21: Допущение: 1–2 дня командировки
A22: Основной канал связи | B22: 3000 | C22: ₽/мес. | D22: Допущение
A23: To-Be: цены и ставки
A24: Облачная касса (SaaS) | B24: 2000 | C24: ₽/касса/мес. | D24: Допущение: рынок облачных касс
A25: Payment Gateway + HAL-агент (SaaS) | B25: 1000 | C25: ₽/терминал/мес. | D25: Допущение
A26: Платформа лояльности (SaaS) | B26: 2000 | C26: ₽/магазин/мес. | D26: Допущение; в As-Is лояльность внутри SAP — удорожание To-Be
A27: Управление планшетами (MDM, SaaS) | B27: 300 | C27: ₽/планшет/мес. | D27: Допущение
A28: Интеграционный слой (PaaS) на всю сеть | B28: 150000 | C28: ₽/мес. | D28: Допущение; на 100 магазинов — доля stores/network
A29: Планшет | B29: 35000 | C29: ₽/шт. | D29: Допущение
A30: Поломка планшетов в год | B30: 0.05 | C30: доля | D30: Допущение
A31: Подменный фонд планшетов | B31: 0.05 | C31: доля | D31: Допущение: замена курьером вместо ремонта
A32: Роутер с резервным LTE | B32: 15000 | C32: ₽/магазин | D32: Допущение
A33: Резервный канал LTE | B33: 1000 | C33: ₽/мес. | D33: Допущение
A34: Инженеры поддержки HQ | B34: 1.5 | C34: чел. на 100 маг. | D34: Допущение: серверов нет, планшеты настраиваются удалённо (MDM)
A35: Вызовов подрядчика на магазин в год | B35: 1 | C35: шт. | D35: Допущение
... A38: Курьерская отправка | B38: 2000 | C38: ₽ | D38: Допущение
A39: To-Be: разовые затраты перехода
A40: Монтаж подрядчиком | B40: 15000 | C40: ₽/магазин | D40: Допущение
A41: Обучение кассиров | B41: 5000 | C41: ₽/магазин | D41: Допущение
A42: Проект внедрения: интеграция с SAP, контракт со шлюзом, пилот | B42: 4000000 | C42: ₽ на 100 маг. | D42: Допущение: доля проекта на всю сеть
A43: Разовые затраты на один магазин | B43: =B7*B29*(1+B31)+B32+B40+B41 -> 108500 | C43: ₽/магазин | D43: Формула: планшеты с подменным фондом + роутер + монтаж + обучение

Sheet TCO
A1: TCO инфраструктуры 100 магазинов: As-Is vs To-Be, ₽
A2: To-Be, год 1 = As-Is в год × (1 − доля) + To-Be в год × доля, где доля — магазино-месяцы на To-Be при раскатке за 12 мес.; разовые затраты — в год 1.
A4: Статья | B4: As-Is, в год | C4: To-Be, в год после раскатки | D4: As-Is · Год 1 | E4: As-Is · Год 2 | F4: As-Is · Год 3 | G4: As-Is · 3 года | H4: To-Be · Год 1 | I4: To-Be · Год 2 | J4: To-Be · Год 3 | K4: To-Be · 3 года | L4: Формула годовой величины
A5: Оборудование (CapEx)
A6: Замена серверов (износ) | B6: =Допущения!$B$5/Допущения!$B$8*Допущения!$B$12 -> 3000000 | C6: 0 | D6: =$B6 -> 3000000 | E6: =$B6 -> 3000000 | F6: =$B6 -> 3000000 | G6: =SUM(D6:F6) -> 9000000 | H6: =$B6*(1-Допущения!$B$10)+$C6*Допущения!$B$10 -> 1375000 | I6: =$C6 -> 0 | J6: =$C6 -> 0 | K6: =SUM(H6:J6) -> 1375000 | L6: магазины / срок службы × цена сервера
A7: Замена ПК касс (износ) | B7: =Допущения!$B$5*Допущения!$B$7/Допущения!$B$8*Допущения!$B$13 -> 2400000 | C7: 0 | D7: =$B7 -> 2400000 | E7: =$B7 -> 2400000 | F7: =$B7 -> 2400000 | G7: =SUM(D7:F7) -> 7200000 | H7: =$B7*(1-Допущения!$B$10)+$C7*Допущения!$B$10 -> 1100000 | I7: =$C7 -> 0 | J7: =$C7 -> 0 | K7: =SUM(H7:J7) -> 1100000 | L7: кассы / срок службы × цена ПК
A8: Замена сломанных планшетов | B8: 0 | C8: =Допущения!$B$5*Допущения!$B$7*Допущения!$B$30*Допущения!$B$29 -> 350000 | D8: =$B8 -> 0 | E8: =$B8 -> 0 | F8: =$B8 -> 0 | G8: =SUM(D8:F8) -> 0 | H8: =$B8*(1-Допущения!$B$10)+$C8*Допущения!$B$10 -> 189583.33 | I8: =$C8 -> 350000 | J8: =$C8 -> 350000 | K8: =SUM(H8:J8) -> 889583.33 | L8: планшеты × доля поломок × цена
A9: Лицензии и подписки (OpEx)
A10: Windows Server к новым серверам | B10: =Допущения!$B$5/Допущения!$B$8*Допущения!$B$14 -> 2400000 | C10: 0 | D10: =$B10 -> 2400000 | E10: =$B10 -> 2400000 | F10: =$B10 -> 2400000 | G10: =SUM(D10:F10) -> 7200000 | H10: =$B10*(1-Допущения!$B$10)+$C10*Допущения!$B$10 -> 1100000 | I10: =$C10 -> 0 | J10: =$C10 -> 0 | K10: =SUM(H10:J10) -> 1100000 | L10: новые серверы × лицензия
A11: SQL Server (не учитываем) | B11: =Допущения!$B$5/Допущения!$B$8*Допущения!$B$15 -> 0 | C11: 0 | D11: =$B11 -> 0 | E11: =$B11 -> 0 | F11: =$B11 -> 0 | G11: =SUM(D11:F11) -> 0 | H11: =$B11*(1-Допущения!$B$10)+$C11*Допущения!$B$10 -> 0 | I11: =$C11 -> 0 | J11: =$C11 -> 0 | K11: =SUM(H11:J11) -> 0 | L11: новые серверы × лицензия SQL (= 0, консервативно)
A12: Резервное копирование и антивирус | B12: =Допущения!$B$5*Допущения!$B$16 -> 800000 | C12: 0 | D12: =$B12 -> 800000 | E12: =$B12 -> 800000 | F12: =$B12 -> 800000 | G12: =SUM(D12:F12) -> 2400000 | H12: =$B12*(1-Допущения!$B$10)+$C12*Допущения!$B$10 -> 366666.67 | I12: =$C12 -> 0 | J12: =$C12 -> 0 | K12: =SUM(H12:J12) -> 366666.67 | L12: магазины × ставка
A13: Сопровождение кассового ПО и драйверов | B13: =Допущения!$B$5*Допущения!$B$7*Допущения!$B$17 -> 2000000 | C13: 0 | D13: =$B13 -> 2000000 | E13: =$B13 -> 2000000 | F13: =$B13 -> 2000000 | G13: =SUM(D13:F13) -> 6000000 | H13: =$B13*(1-Допущения!$B$10)+$C13*Допущения!$B$10 -> 916666.67 | I13: =$C13 -> 0 | J13: =$C13 -> 0 | K13: =SUM(H13:J13) -> 916666.67 | L13: кассы × ставка
A14: Облачная касса (SaaS) | B14: 0 | C14: =Допущения!$B$5*Допущения!$B$7*Допущения!$B$24*12 -> 4800000 | D14: =$B14 -> 0 | E14: =$B14 -> 0 | F14: =$B14 -> 0 | G14: =SUM(D14:F14) -> 0 | H14: =$B14*(1-Допущения!$B$10)+$C14*Допущения!$B$10 -> 2600000 | I14: =$C14 -> 4800000 | J14: =$C14 -> 4800000 | K14: =SUM(H14:J14) -> 12200000 | L14: кассы × ₽/мес × 12
A15: Payment Gateway + HAL-агент (SaaS) | B15: 0 | C15: =Допущения!$B$5*Допущения!$B$7*Допущения!$B$25*12 -> 2400000 | D15: =$B15 -> 0 | E15: =$B15 -> 0 | F15: =$B15 -> 0 | G15: =SUM(D15:F15) -> 0 | H15: =$B15*(1-Допущения!$B$10)+$C15*Допущения!$B$10 -> 1300000 | I15: =$C15 -> 2400000 | J15: =$C15 -> 2400000 | K15: =SUM(H15:J15) -> 6100000 | L15: терминалы × ₽/мес × 12
A16: Платформа лояльности (SaaS) | B16: 0 | C16: =Допущения!$B$5*Допущения!$B$26*12 -> 2400000 | D16: =$B16 -> 0 | E16: =$B16 -> 0 | F16: =$B16 -> 0 | G16: =SUM(D16:F16) -> 0 | H16: =$B16*(1-Допущения!$B$10)+$C16*Допущения!$B$10 -> 1300000 | I16: =$C16 -> 2400000 | J16: =$C16 -> 2400000 | K16: =SUM(H16:J16) -> 6100000 | L16: магазины × ₽/мес × 12
A17: MDM планшетов (SaaS) | B17: 0 | C17: =Допущения!$B$5*Допущения!$B$7*Допущения!$B$27*12 -> 720000 | D17: =$B17 -> 0 | E17: =$B17 -> 0 | F17: =$B17 -> 0 | G17: =SUM(D17:F17) -> 0 | H17: =$B17*(1-Допущения!$B$10)+$C17*Допущения!$B$10 -> 390000 | I17: =$C17 -> 720000 | J17: =$C17 -> 720000 | K17: =SUM(H17:J17) -> 1830000 | L17: планшеты × ₽/мес × 12
A18: Интеграционный слой (PaaS), доля | B18: 0 | C18: =Допущения!$B$28*12*Допущения!$B$5/Допущения!$B$6 -> 360000 | D18: =$B18 -> 0 | E18: =$B18 -> 0 | F18: =$B18 -> 0 | G18: =SUM(D18:F18) -> 0 | H18: =$B18*(1-Допущения!$B$10)+$C18*Допущения!$B$10 -> 195000 | I18: =$C18 -> 360000 | J18: =$C18 -> 360000 | K18: =SUM(H18:J18) -> 915000 | L18: ₽/мес × 12 × магазины / магазинов в сети
A19: ФОТ поддержки
A20: Инженеры поддержки | B20: =Допущения!$B$18*Допущения!$B$19*12 -> 9600000 | C20: =Допущения!$B$34*Допущения!$B$19*12 -> 3600000 | D20: =$B20 -> 9600000 | E20: =$B20 -> 9600000 | F20: =$B20 -> 9600000 | G20: =SUM(D20:F20) -> 28800000 | H20: =$B20*(1-Допущения!$B$10)+$C20*Допущения!$B$10 -> 6350000 | I20: =$C20 -> 3600000 | J20: =$C20 -> 3600000 | K20: =SUM(H20:J20) -> 13550000 | L20: инженеры × ₽/мес × 12
A21: Выезды и командировки поддержки
A22: Командировки инженеров HQ | B22: =Допущения!$B$5*Допущения!$B$20*Допущения!$B$21 -> 4500000 | C22: 0 | D22: =$B22 -> 4500000 | E22: =$B22 -> 4500000 | F22: =$B22 -> 4500000 | G22: =SUM(D22:F22) -> 13500000 | H22: =$B22*(1-Допущения!$B$10)+$C22*Допущения!$B$10 -> 2062500 | I22: =$C22 -> 0 | J22: =$C22 -> 0 | K22: =SUM(H22:J22) -> 2062500 | L22: магазины × выезды × стоимость
A23: Региональный подрядчик и курьер | B23: 0 | C23: =Допущения!$B$5*(Допущения!$B$35*Допущения!$B$36+Допущения!$B$37*Допущения!$B$38) -> 800000 | D23: =$B23 -> 0 | E23: =$B23 -> 0 | F23: =$B23 -> 0 | G23: =SUM(D23:F23) -> 0 | H23: =$B23*(1-Допущения!$B$10)+$C23*Допущения!$B$10 -> 433333.33 | I23: =$C23 -> 800000 | J23: =$C23 -> 800000 | K23: =SUM(H23:J23) -> 2033333.3 | L23: магазины × (вызовы × ставка + отправки × курьер)
A24: Каналы связи
A25: Связь магазинов | B25: =Допущения!$B$5*Допущения!$B$22*12 -> 3600000 | C25: =Допущения!$B$5*(Допущения!$B$22+Допущения!$B$33)*12 -> 4800000 | D25: =$B25 -> 3600000 | E25: =$B25 -> 3600000 | F25: =$B25 -> 3600000 | G25: =SUM(D25:F25) -> 10800000 | H25: =$B25*(1-Допущения!$B$10)+$C25*Допущения!$B$10 -> 4250000 | I25: =$C25 -> 4800000 | J25: =$C25 -> 4800000 | K25: =SUM(H25:J25) -> 13850000 | L25: магазины × каналы ₽/мес × 12
A26: Разовые затраты перехода
A27: Планшеты и подменный фонд | B27: 0 | C27: 0 | D27: 0 | E27: 0 | F27: 0 | G27: 0 | H27: =Допущения!$B$5*Допущения!$B$7*Допущения!$B$29*(1+Допущения!$B$31) -> 7350000 | I27: 0 | J27: 0 | K27: =SUM(H27:J27) -> 7350000 | L27: разово, в год 1
A28: Роутеры с LTE | B28: 0 | C28: 0 | D28: 0 | E28: 0 | F28: 0 | G28: 0 | H28: =Допущения!$B$5*Допущения!$B$32 -> 1500000 | I28: 0 | J28: 0 | K28: =SUM(H28:J28) -> 1500000 | L28: разово, в год 1
A29: Монтаж подрядчиком | B29: 0 | C29: 0 | D29: 0 | E29: 0 | F29: 0 | G29: 0 | H29: =Допущения!$B$5*Допущения!$B$40 -> 1500000 | I29: 0 | J29: 0 | K29: =SUM(H29:J29) -> 1500000 | L29: разово, в год 1
A30: Обучение кассиров | B30: 0 | C30: 0 | D30: 0 | E30: 0 | F30: 0 | G30: 0 | H30: =Допущения!$B$5*Допущения!$B$41 -> 500000 | I30: 0 | J30: 0 | K30: =SUM(H30:J30) -> 500000 | L30: разово, в год 1
A31: Проект внедрения (доля) | B31: 0 | C31: 0 | D31: 0 | E31: 0 | F31: 0 | G31: 0 | H31: =Допущения!$B$42 -> 4000000 | I31: 0 | J31: 0 | K31: =SUM(H31:J31) -> 4000000 | L31: разово, в год 1
A32: ИТОГО | B32: =SUM(B5:B31) -> 28300000 | C32: =SUM(C5:C31) -> 20230000 | D32: =SUM(D5:D31) -> 28300000 | E32: =SUM(E5:E31) -> 28300000 | F32: =SUM(F5:F31) -> 28300000 | G32: =SUM(G5:G31) -> 84900000 | H32: =SUM(H5:H31) -> 38778750 | I32: =SUM(I5:I31) -> 20230000 | ... K32: =SUM(K5:K31) -> 79238750
A34: Сводка
A35: TCO As-Is за 3 года, ₽ | B35: =G32 -> 84900000
A36: TCO To-Be за 3 года, ₽ | B36: =K32 -> 79238750
A37: Чистая экономия за 3 года (с учётом разовых затрат), ₽ | B37: =G32-K32 -> 5661250
A38: Разовые затраты перехода, ₽ | B38: =SUM(H27,H28,H29,H30,H31) -> 14850000
A39: ROI за 3 года (чистая экономия / разовые затраты) | B39: =IF(B38=0,0,(B37)/B38) -> 0.38122896
A40: Годовой TCO после раскатки: снижение | B40: =IF(B32=0,0,(B32-C32)/B32) -> 0.28515901
A41: ИТ-поддержка (ФОТ + выезды) после раскатки: снижение | B41: =IF((B20+B22+B23)=0,0,((B20+B22+B23)-(C20+C22+C23))/(B20+B22+B23)) -> 0.68794326
A42: Окупаемость (break-even), месяц | B42: =Окупаемость!$J$2 -> 28

Sheet Окупаемость
A1: Накопленный денежный поток перехода, ₽ (экономия переведённых магазинов − разовые затраты)
I2: Месяц окупаемости: | J2: =IF(COUNT(H6:H41)=0,"не окупается за 3 года",MIN(H6:H41)) -> 28
A3: Экономия переведённого магазина в месяц, ₽ | C3: =(TCO!B32-TCO!C32)/Допущения!$B$5/12 -> 6725
A5: Месяц | B5: Переведено в месяце | C5: Всего переведено | D5: Разовые затраты | E5: Экономия | F5: Денежный поток | G5: Накоплено | H5: Окупился в этом месяце
A6: 1 | B6: =IF(A6<=Допущения!$B$9,Допущения!$B$5/Допущения!$B$9,0) -> 8.3333333 | C6: =B6 -> 8.3333333 | D6: =B6*Допущения!$B$43+IF(A6=1,Допущения!$B$42,0) -> 4904166.7 | E6: =C6*$C$3 -> 56041.667 | F6: =E6-D6 -> -4848125 | G6: =F6 -> -4848125 | H6: =IF(G6>=0,A6,"")
A7: 2 | B7: =IF(A7<=Допущения!$B$9,Допущения!$B$5/Допущения!$B$9,0) -> 8.3333333 | C7: =C6+B7 -> 16.666667 | D7: =B7*Допущения!$B$43+IF(A7=1,Допущения!$B$42,0) -> 904166.67 | E7: =C7*$C$3 -> 112083.33 | F7: =E7-D7 -> -792083.33 | G7: =G6+F7 -> -5640208.3 | H7: =IF(AND(G7>=0,G6<0),A7,"")
A8: 3 | B8: =IF(A8<=Допущения!$B$9,Допущения!$B$5/Допущения!$B$9,0) -> 8.3333333 | C8: =C7+B8 -> 25 | D8: =B8*Допущения!$B$43+IF(A8=1,Допущения!$B$42,0) -> 904166.67 | E8: =C8*$C$3 -> 168125 | F8: =E8-D8 -> -736041.67 | G8: =G7+F8 -> -6376250 | H8: =IF(AND(G8>=0,G7<0),A8,"")
A9: 4 | B9: =IF(A9<=Допущения!$B$9,Допущения!$B$5/Допущения!$B$9,0) -> 8.3333333 | C9: =C8+B9 -> 33.333333 | D9: =B9*Допущения!$B$43+IF(A9=1,Допущения!$B$42,0) -> 904166.67 | E9: =C9*$C$3 -> 224166.67 | F9: =E9-D9 -> -680000 | G9: =G8+F9 -> -7056250 | H9: =IF(AND(G9>=0,G8<0),A9,"")
A10: 5 | B10: =IF(A10<=Допущения!$B$9,Допущения!$B$5/Допущения!$B$9,0) -> 8.3333333 | C10: =C9+B10 -> 41.666667 | D10: =B10*Допущения!$B$43+IF(A10=1,Допущения!$B$42,0) -> 904166.67 | E10: =C10*$C$3 -> 280208.33 | F10: =E10-D10 -> -623958.33 | G10: =G9+F10 -> -7680208.3 | H10: =IF(AND(G10>=0,G9<0),A10,"")
A11: 6 | B11: =IF(A11<=Допущения!$B$9,Допущения!$B$5/Допущения!$B$9,0) -> 8.3333333 | C11: =C10+B11 -> 50 | D11: =B11*Допущения!$B$43+IF(A11=1,Допущения!$B$42,0) -> 904166.67 | E11: =C11*$C$3 -> 336250 | F11: =E11-D11 -> -567916.67 | G11: =G10+F11 -> -8248125 | H11: =IF(AND(G11>=0,G10<0),A11,"")
A12: 7 | B12: =IF(A12<=Допущения!$B$9,Допущения!$B$5/Допущения!$B$9,0) -> 8.3333333 | C12: =C11+B12 -> 58.333333 | D12: =B12*Допущения!$B$43+IF(A12=1,Допущения!$B$42,0) -> 904166.67 | E12: =C12*$C$3 -> 392291.67 | F12: =E12-D12 -> -511875 | G12: =G11+F12 -> -8760000 | H12: =IF(AND(G12>=0,G11<0),A12,"")
A13: 8 | B13: =IF(A13<=Допущения!$B$9,Допущения!$B$5/Допущения!$B$9,0) -> 8.3333333 | C13: =C12+B13 -> 66.666667 | D13: =B13*Допущения!$B$43+IF(A13=1,Допущения!$B$42,0) -> 904166.67 | E13: =C13*$C$3 -> 448333.33 | F13: =E13-D13 -> -455833.33 | G13: =G12+F13 -> -9215833.3 | H13: =IF(AND(G13>=0,G12<0),A13,"")
A14: 9 | B14: =IF(A14<=Допущения!$B$9,Допущения!$B$5/Допущения!$B$9,0) -> 8.3333333 | C14: =C13+B14 -> 75 | D14: =B14*Допущения!$B$43+IF(A14=1,Допущения!$B$42,0) -> 904166.67 | E14: =C14*$C$3 -> 504375 | F14: =E14-D14 -> -399791.67 | G14: =G13+F14 -> -9615625 | H14: =IF(AND(G14>=0,G13<0),A14,"")
A15: 10 | B15: =IF(A15<=Допущения!$B$9,Допущения!$B$5/Допущения!$B$9,0) -> 8.3333333 | C15: =C14+B15 -> 83.333333 | D15: =B15*Допущения!$B$43+IF(A15=1,Допущения!$B$42,0) -> 904166.67 | E15: =C15*$C$3 -> 560416.67 | F15: =E15-D15 -> -343750 | G15: =G14+F15 -> -9959375 | H15: =IF(AND(G15>=0,G14<0),A15,"")
A16: 11 | B16: =IF(A16<=Допущения!$B$9,Допущения!$B$5/Допущения!$B$9,0) -> 8.3333333 | C16: =C15+B16 -> 91.666667 | D16: =B16*Допущения!$B$43+IF(A16=1,Допущения!$B$42,0) -> 904166.67 | E16: =C16*$C$3 -> 616458.33 | F16: =E16-D16 -> -287708.33 | G16: =G15+F16 -> -10247083 | H16: =IF(AND(G16>=0,G15<0),A16,"")
A17: 12 | B17: =IF(A17<=Допущения!$B$9,Допущения!$B$5/Допущения!$B$9,0) -> 8.3333333 | C17: =C16+B17 -> 100 | D17: =B17*Допущения!$B$43+IF(A17=1,Допущения!$B$42,0) -> 904166.67 | E17: =C17*$C$3 -> 672500 | F17: =E17-D17 -> -231666.67 | G17: =G16+F17 -> -10478750 | H17: =IF(AND(G17>=0,G16<0),A17,"")
A18: 13 | B18: =IF(A18<=Допущения!$B$9,Допущения!$B$5/Допущения!$B$9,0) -> 0 | C18: =C17+B18 -> 100 | D18: =B18*Допущения!$B$43+IF(A18=1,Допущения!$B$42,0) -> 0 | E18: =C18*$C$3 -> 672500 | F18: =E18-D18 -> 672500 | G18: =G17+F18 -> -9806250 | H18: =IF(AND(G18>=0,G17<0),A18,"")
... A41: 36 | B41: =IF(A41<=Допущения!$B$9,Допущения!$B$5/Допущения!$B$9,0) -> 0 | C41: =C40+B41 -> 100 | D41: =B41*Допущения!$B$43+IF(A41=1,Допущения!$B$42,0) -> 0 | E41: =C41*$C$3 -> 672500 | F41: =E41-D41 -> 672500 | G41: =G40+F41 -> 5661250 | H41: =IF(AND(G41>=0,G40<0),A41,"")
